irradiant/__init__.py
irradiant/networking/AsyncStreamServer.py
irradiant/networking/__init__.py
irradiant-0.0.1.dist-info/METADATA
irradiant-0.0.1.dist-info/WHEEL
irradiant-0.0.1.dist-info/top_level.txt
irradiant-0.0.1.dist-info/RECORD
