Metadata-Version: 2.1
Name: irradiant
Version: 0.0.1
Summary: Assorted collection of utilities provided by Irradiant.
Home-page: UNKNOWN
Author: Pieter Robyns
Author-email: pieter.robyns@outlook.com
License: MIT License
Platform: UNKNOWN
